shadowsocks/__init__.py
shadowsocks/asyncdns.py
shadowsocks/common.py
shadowsocks/cryptor.py
shadowsocks/daemon.py
shadowsocks/eventloop.py
shadowsocks/local.py
shadowsocks/lru_cache.py
shadowsocks/manager.py
shadowsocks/server.py
shadowsocks/shell.py
shadowsocks/tcprelay.py
shadowsocks/tunnel.py
shadowsocks/udprelay.py
shadowsocks/crypto/__init__.py
shadowsocks/crypto/aead.py
shadowsocks/crypto/hkdf.py
shadowsocks/crypto/mbedtls.py
shadowsocks/crypto/openssl.py
shadowsocks/crypto/rc4_md5.py
shadowsocks/crypto/sodium.py
shadowsocks/crypto/table.py
shadowsocks/crypto/util.py
shadowsocks_legacy-3.0.1.dist-info/LICENSE
shadowsocks_legacy-3.0.1.dist-info/METADATA
shadowsocks_legacy-3.0.1.dist-info/WHEEL
shadowsocks_legacy-3.0.1.dist-info/entry_points.txt
shadowsocks_legacy-3.0.1.dist-info/top_level.txt
shadowsocks_legacy-3.0.1.dist-info/RECORD
